gputranad-0.1.0.dist-info/METADATA
gputranad-0.1.0.dist-info/WHEEL
gputranad-0.1.0.dist-info/licenses/LICENSE
gputranad/__init__.py
gputranad/models.py
gputranad/preprocess.py
gputranad-0.1.0.dist-info/RECORD
